systemlookup
